odoo/addons/partner_interest_group/README.rst
odoo/addons/partner_interest_group/__init__.py
odoo/addons/partner_interest_group/__manifest__.py
odoo/addons/partner_interest_group/i18n/es.po
odoo/addons/partner_interest_group/i18n/fi.po
odoo/addons/partner_interest_group/i18n/fr.po
odoo/addons/partner_interest_group/i18n/it.po
odoo/addons/partner_interest_group/i18n/partner_interest_group.pot
odoo/addons/partner_interest_group/models/__init__.py
odoo/addons/partner_interest_group/models/res_partner.py
odoo/addons/partner_interest_group/models/res_partner_interest_group.py
odoo/addons/partner_interest_group/readme/CONTRIBUTORS.rst
odoo/addons/partner_interest_group/readme/DESCRIPTION.rst
odoo/addons/partner_interest_group/security/interest_group_rules.xml
odoo/addons/partner_interest_group/security/ir.model.access.csv
odoo/addons/partner_interest_group/static/description/icon.png
odoo/addons/partner_interest_group/static/description/index.html
odoo/addons/partner_interest_group/views/res_partner_interest_group_view.xml
odoo/addons/partner_interest_group/views/res_partner_view.xml
odoo_addon_partner_interest_group-16.0.1.2.0.2.dist-info/METADATA
odoo_addon_partner_interest_group-16.0.1.2.0.2.dist-info/WHEEL
odoo_addon_partner_interest_group-16.0.1.2.0.2.dist-info/top_level.txt
odoo_addon_partner_interest_group-16.0.1.2.0.2.dist-info/RECORD
